sam_serve/__about__.py
sam_serve/__init__.py
sam_serve/decode.py
sam_serve/encode.py
sam_serve/utils.py
sam_serve-1.1.0.dist-info/METADATA
sam_serve-1.1.0.dist-info/WHEEL
sam_serve-1.1.0.dist-info/licenses/LICENSE
sam_serve-1.1.0.dist-info/RECORD
